dvcr/__init__.py
dvcr/network.py
dvcr/socket.py
dvcr/utils.py
dvcr/containers/__init__.py
dvcr/containers/airflow.py
dvcr/containers/base.py
dvcr/containers/cassandra.py
dvcr/containers/kafka.py
dvcr/containers/mysql.py
dvcr/containers/postgres.py
dvcr/containers/prometheus.py
dvcr/containers/rabbitmq.py
dvcr/containers/redis.py
dvcr/containers/vertica.py
dvcr/containers/zookeeper.py
dvcr-0.4.0.dist-info/METADATA
dvcr-0.4.0.dist-info/WHEEL
dvcr-0.4.0.dist-info/top_level.txt
dvcr-0.4.0.dist-info/RECORD
